facebook_plugin_banyan/__init__.py
facebook_plugin_banyan/facebook_plugin.py
facebook_plugin_banyan-0.0.18.dist-info/entry_points.txt
facebook_plugin_banyan-0.0.18.dist-info/METADATA
facebook_plugin_banyan-0.0.18.dist-info/WHEEL
facebook_plugin_banyan-0.0.18.dist-info/RECORD
