Metadata-Version: 2.3
Name: facebook_plugin_banyan
Version: 0.0.18
Summary: 
Author: chuck yang
Author-email: yzhang.baby@gmail.com
Requires-Python: >=3.11, <4.0
Classifier: Programming Language :: Python :: 3
Classifier: Programming Language :: Python :: 3.11
Classifier: Programming Language :: Python :: 3.12
Classifier: Programming Language :: Python :: 3.13
Requires-Dist: xcmap (>=0.0.1)
